cotinga/__init__.py
cotinga/application.py
cotinga/core/__init__.py
cotinga/core/constants.py
cotinga/core/database.py
cotinga/core/doc_setup.py
cotinga/core/document.py
cotinga/core/env.py
cotinga/core/errors.py
cotinga/core/io.py
cotinga/core/mathmaker.py
cotinga/core/merge_tex.py
cotinga/core/operations.py
cotinga/core/prefs.py
cotinga/core/presets.py
cotinga/core/recollections.py
cotinga/core/report.py
cotinga/core/status.py
cotinga/core/tools.py
cotinga/data/cotinga.desktop
cotinga/data/default/doc_setup/en_US.json
cotinga/data/default/doc_setup/fr_FR.json
cotinga/data/default/prefs.json
cotinga/data/default/recollections.json
cotinga/data/default/status.json
cotinga/data/flags/FR.svg
cotinga/data/flags/US.svg
cotinga/data/icons/cotinga.svg
cotinga/data/icons/cotinga_bw.svg
cotinga/data/icons/cotinga_bw_faded.svg
cotinga/data/icons/cotinga_faded.svg
cotinga/data/icons/cotinga_numix_circle.svg
cotinga/data/icons/cotinga_numix_square.svg
cotinga/data/locale/cotinga.pot
cotinga/data/locale/en_US/LC_MESSAGES/cotinga.mo
cotinga/data/locale/en_US/LC_MESSAGES/cotinga.po
cotinga/data/locale/fr_FR/LC_MESSAGES/cotinga.mo
cotinga/data/locale/fr_FR/LC_MESSAGES/cotinga.po
cotinga/data/pyproject.toml
cotinga/gui/__init__.py
cotinga/gui/app_menu.xml
cotinga/gui/core/__init__.py
cotinga/gui/core/classes_stacked.py
cotinga/gui/core/icons_themable.py
cotinga/gui/core/list_manager/__init__.py
cotinga/gui/core/list_manager/list_manager_base.py
cotinga/gui/core/list_manager/list_manager_panel.py
cotinga/gui/core/list_manager/presets_combo.py
cotinga/gui/core/pupils_view.py
cotinga/gui/core/sharee.py
cotinga/gui/dialogs/__init__.py
cotinga/gui/dialogs/combo.py
cotinga/gui/dialogs/confirmation.py
cotinga/gui/dialogs/doc_setup/__init__.py
cotinga/gui/dialogs/doc_setup/classes_manager_panel.py
cotinga/gui/dialogs/doc_setup/doc_setup.py
cotinga/gui/dialogs/doc_setup/grading_manager.py
cotinga/gui/dialogs/doc_setup/literal_grading_panel.py
cotinga-0.2.7.dist-info/LICENSE
cotinga-0.2.7.dist-info/METADATA
cotinga-0.2.7.dist-info/WHEEL
cotinga-0.2.7.dist-info/entry_points.txt
cotinga-0.2.7.dist-info/RECORD
