Metadata-Version: 2.3
Name: cotinga
Version: 0.2.7
Summary: Teachers' helper to manage their pupils' progression.
License: GPL-3.0-or-later
Author: Nicolas Hainaux
Author-email: nh.techn@posteo.net
Requires-Python: >=3.9,<4.0
Classifier: Development Status :: 4 - Beta
Classifier: Environment :: X11 Applications :: GTK
Classifier: Intended Audience :: Education
Classifier: Intended Audience :: End Users/Desktop
Classifier: License :: OSI Approved :: GNU General Public License v3 or later (GPLv3+)
Classifier: Natural Language :: English
Classifier: Natural Language :: French
Classifier: Operating System :: POSIX :: Linux
Classifier: Programming Language :: Python :: 3
Classifier: Programming Language :: Python :: 3.9
Classifier: Programming Language :: Python :: 3.10
Classifier: Programming Language :: Python :: 3.11
Classifier: Programming Language :: Python :: 3.12
Classifier: Programming Language :: Python :: 3.13
Classifier: Topic :: Education
Requires-Dist: Babel (>=2.9.1,<3.0.0)
Requires-Dist: microlib (>=1.8.0,<2.0.0)
Requires-Dist: pikepdf (>=5.0.1,<6.0.0)
Requires-Dist: pygobject (>=3.42,<4.0)
Requires-Dist: python-magic (>=0.4.25,<0.5.0)
Requires-Dist: reportlab (>=3.6.7,<4.0.0)
Requires-Dist: sqlalchemy (>=1.4.31,<2.0.0)
Requires-Dist: sqlalchemy-utils (>=0.38.2,<0.39.0)
Requires-Dist: toml (>=0.10.2,<0.11.0)
Requires-Dist: wheel (>=0.37.1,<0.38.0)
Project-URL: Repository, https://gitlab.com/nicolas.hainaux/cotinga
